alog/__init__.py
alog/alog.py
alog/protocols.py
alchemy_logging-1.5.1.dist-info/METADATA
alchemy_logging-1.5.1.dist-info/WHEEL
alchemy_logging-1.5.1.dist-info/top_level.txt
alchemy_logging-1.5.1.dist-info/RECORD
