Metadata-Version: 2.1
Name: alchemy-logging
Version: 1.5.1
Summary: A wrapper around the logging package to provide Alchemy Logging functionality
Home-page: https://github.com/IBM/alchemy-logging
Author: Gabe Goodhart
Author-email: gabe.l.hart@gmail.com
License: MIT
Keywords: logging
Platform: UNKNOWN
Classifier: Intended Audience :: Developers
Classifier: Topic :: Software Development :: User Interfaces
Classifier: Programming Language :: Python :: 3
Classifier: Programming Language :: Python :: 3.5
Classifier: Programming Language :: Python :: 3.6
Classifier: Programming Language :: Python :: 3.7
Classifier: Programming Language :: Python :: 3.8
Classifier: Programming Language :: Python :: 3.9
Classifier: Programming Language :: Python :: 3.10
Requires-Dist: typing-extensions ; python_version < "3.8"
